EPCPyYes/__init__.py
EPCPyYes/core/__init__.py
EPCPyYes/core/errors.py
EPCPyYes/core/SBDH/__init__.py
EPCPyYes/core/SBDH/sbdh.py
EPCPyYes/core/SBDH/template_sbdh.py
EPCPyYes/core/tests/__init__.py
EPCPyYes/core/tests/test_cbv_helpers.py
EPCPyYes/core/tests/test_helpers.py
EPCPyYes/core/tests/test_template_events.py
EPCPyYes/core/tests/test_utils.py
EPCPyYes/core/tests/schemas/BasicTypes.xsd
EPCPyYes/core/tests/schemas/BusinessScope.xsd
EPCPyYes/core/tests/schemas/DocumentIdentification.xsd
EPCPyYes/core/tests/schemas/EPCglobal-epcis-1_2.xsd
EPCPyYes/core/tests/schemas/EPCglobal-epcis-masterdata-1_2.xsd
EPCPyYes/core/tests/schemas/EPCglobal-epcis-query-1_2.wsdl
EPCPyYes/core/tests/schemas/EPCglobal-epcis-query-1_2.xsd
EPCPyYes/core/tests/schemas/EPCglobal.xsd
EPCPyYes/core/tests/schemas/Manifest.xsd
EPCPyYes/core/tests/schemas/Partner.xsd
EPCPyYes/core/tests/schemas/StandardBusinessDocumentHeader.xsd
EPCPyYes/core/v1_2/__init__.py
EPCPyYes/core/v1_2/events.py
EPCPyYes/core/v1_2/helpers.py
EPCPyYes/core/v1_2/json_decoders.py
EPCPyYes/core/v1_2/json_encoders.py
EPCPyYes/core/v1_2/template_events.py
EPCPyYes/core/v1_2/CBV/__init__.py
EPCPyYes/core/v1_2/CBV/business_steps.py
EPCPyYes/core/v1_2/CBV/business_transactions.py
EPCPyYes/core/v1_2/CBV/dispositions.py
EPCPyYes/core/v1_2/CBV/error_reasons.py
EPCPyYes/core/v1_2/CBV/helpers.py
EPCPyYes/core/v1_2/CBV/instance_lot_master_data.py
EPCPyYes/core/v1_2/CBV/location_party_master_data.py
EPCPyYes/core/v1_2/CBV/source_destination.py
EPCPyYes/templates/epcis/aggregation_event.xml
EPCPyYes/templates/epcis/base_extension.xml
EPCPyYes/templates/epcis/biz_transaction_list.xml
EPCPyYes/templates/epcis/business_data.xml
EPCPyYes/templates/epcis/child_quantity_list.xml
EPCPyYes/templates/epcis/destination_list.xml
EPCPyYes/templates/epcis/epcis_document.xml
EPCPyYes/templates/epcis/epcis_events_document.xml
EPCPyYes/templates/epcis/event_times.xml
EPCPyYes/templates/epcis/extension.xml
EPCPyYes/templates/epcis/ilmd.xml
EPCPyYes-4.0.3.dist-info/AUTHORS.rst
EPCPyYes-4.0.3.dist-info/LICENSE.md
EPCPyYes-4.0.3.dist-info/METADATA
EPCPyYes-4.0.3.dist-info/WHEEL
EPCPyYes-4.0.3.dist-info/top_level.txt
EPCPyYes-4.0.3.dist-info/RECORD
