Metadata-Version: 2.1
Name: EPCPyYes
Version: 4.0.3
Summary: EPCIS Python module for quickly developing EPCIS-enabled applications.
Home-page: https://gitlab.com/serial-lab/EPCPyYes
Author: Serial Lab
Author-email: slab@serial-lab.com
Maintainer: Rob Magee
License: GNU Affero General Public License v3
Keywords: EPCPyYes EPCIS GS1 RFID Serialization
Platform: UNKNOWN
Classifier: Development Status :: 5 - Production/Stable
Classifier: Intended Audience :: Healthcare Industry
Classifier: Intended Audience :: Manufacturing
Classifier: Intended Audience :: Developers
Classifier: License :: OSI Approved :: GNU Affero General Public License v3 or later (AGPLv3+)
Classifier: Natural Language :: English
Classifier: Programming Language :: Python :: 3
Classifier: Programming Language :: Python :: 3.5
Classifier: Programming Language :: Python :: 3.6
Classifier: Programming Language :: Python :: 3.7
Requires-Dist: Jinja2
Requires-Dist: commonmark
Requires-Dist: lxml
